README.md
setup.py
bin/dbcon
dbcon/__init__.py
dbcon/cli.py
dbcon/util.py
dbcon.egg-info/PKG-INFO
dbcon.egg-info/SOURCES.txt
dbcon.egg-info/dependency_links.txt
dbcon.egg-info/top_level.txt
dbcon/dbms/__init__.py
dbcon/dbms/postgres.py