Metadata-Version: 1.1
Name: dbcon
Version: 0.0.2
Summary: Database configuration tool for database-backed applications
Home-page: https://github.com/youngrok/dbcon
Author: Youngrok Pak
Author-email: pak.youngrok@gmail.com
License: UNKNOWN
Keywords: database configuration django yaml connection
Platform: UNKNOWN
Classifier: Development Status :: 3 - Alpha
Classifier: Topic :: Software Development :: Libraries
Classifier: License :: OSI Approved :: BSD License
